esql/__init__.py
esql/__main__.py
esql-2.2.dist-info/METADATA
esql-2.2.dist-info/WHEEL
esql-2.2.dist-info/top_level.txt
esql-2.2.dist-info/RECORD
