Metadata-Version: 2.1
Name: esql
Version: 2.2
Summary: a SQL helper
Home-page: https://github.com/Morgandri1/esql
Author: Morgan Metz
Author-email: mlmi4@k12albemarle.org
Project-URL: Bug Tracker, https://github.com/Morgandri1/esql/issues
Classifier: Programming Language :: Python :: 3
Classifier: License :: OSI Approved :: MIT License
Classifier: Operating System :: OS Independent
Requires-Python: >=3.0
